autoevals/__init__.py
autoevals/json.py
autoevals/list.py
autoevals/llm.py
autoevals/moderation.py
autoevals/number.py
autoevals/oai.py
autoevals/partial.py
autoevals/ragas.py
autoevals/string.py
autoevals/test_embeddings.py
autoevals/test_json.py
autoevals/test_llm.py
autoevals/test_moderation.py
autoevals/test_oai.py
autoevals/test_partial.py
autoevals/test_ragas.py
autoevals/test_values.py
autoevals/value.py
autoevals/version.py
autoevals/templates/battle.yaml
autoevals/templates/closed_q_a.yaml
autoevals/templates/factuality.yaml
autoevals/templates/humor.yaml
autoevals/templates/possible.yaml
autoevals/templates/security.yaml
autoevals/templates/sql.yaml
autoevals/templates/summary.yaml
autoevals/templates/translation.yaml
autoevals-0.0.129.dist-info/licenses/LICENSE
autoevals-0.0.129.dist-info/METADATA
autoevals-0.0.129.dist-info/WHEEL
autoevals-0.0.129.dist-info/top_level.txt
autoevals-0.0.129.dist-info/RECORD
