Metadata-Version: 2.4
Name: autoevals
Version: 0.0.129
Summary: Universal library for evaluating AI models
Home-page: https://www.braintrustdata.com
Author: BrainTrust
Author-email: info@braintrustdata.com
Project-URL: Bug Tracker, https://github.com/braintrustdata/autoevals
Classifier: Programming Language :: Python :: 3
Classifier: Operating System :: OS Independent
Requires-Python: >=3.8.0
License-File: LICENSE
Requires-Dist: chevron
Requires-Dist: polyleven
Requires-Dist: pyyaml
Requires-Dist: braintrust_core==0.0.59
Requires-Dist: jsonschema
Provides-Extra: dev
Requires-Dist: black==22.6.0; extra == "dev"
Requires-Dist: braintrust; extra == "dev"
Requires-Dist: build; extra == "dev"
Requires-Dist: flake8; extra == "dev"
Requires-Dist: flake8-isort; extra == "dev"
Requires-Dist: IPython; extra == "dev"
Requires-Dist: isort==5.12.0; extra == "dev"
Requires-Dist: openai; extra == "dev"
Requires-Dist: pre-commit; extra == "dev"
Requires-Dist: pytest; extra == "dev"
Requires-Dist: respx; extra == "dev"
Requires-Dist: twine; extra == "dev"
Provides-Extra: doc
Requires-Dist: pydoc-markdown; extra == "doc"
Provides-Extra: scipy
Requires-Dist: numpy; extra == "scipy"
Requires-Dist: scipy; extra == "scipy"
Provides-Extra: all
Requires-Dist: IPython; extra == "all"
Requires-Dist: black==22.6.0; extra == "all"
Requires-Dist: braintrust; extra == "all"
Requires-Dist: build; extra == "all"
Requires-Dist: flake8; extra == "all"
Requires-Dist: flake8-isort; extra == "all"
Requires-Dist: isort==5.12.0; extra == "all"
Requires-Dist: numpy; extra == "all"
Requires-Dist: openai; extra == "all"
Requires-Dist: pre-commit; extra == "all"
Requires-Dist: pydoc-markdown; extra == "all"
Requires-Dist: pytest; extra == "all"
Requires-Dist: respx; extra == "all"
Requires-Dist: scipy; extra == "all"
Requires-Dist: twine; extra == "all"
Dynamic: author
Dynamic: author-email
Dynamic: classifier
Dynamic: description
Dynamic: description-content-type
Dynamic: home-page
Dynamic: license-file
Dynamic: project-url
Dynamic: provides-extra
Dynamic: requires-dist
Dynamic: requires-python
Dynamic: summary
